{
  "id": "daikin-ekwhctrl1",
  "name": "Daikin EKWHCTRL1 / EKRTCTRL1",
  "serial": { "baud": 9600, "dataBits": 8, "parity": "none", "stopBits": 1 },
  "functions": ["FC03", "FC06"],
  "registers": [
    { "addr": 0, "mnem": "T1", "name": "Temp. powietrza", "access": "R", "type": "uint16", "scale": 0.1, "unit": "°C" },
    { "addr": 1, "mnem": "T2", "name": "Temp. wody H2", "access": "R", "type": "uint16", "scale": 0.1, "unit": "°C" },
    { "addr": 8, "mnem": "SP", "name": "Setpoint rzeczywisty", "access": "R", "type": "uint16", "scale": 0.1, "unit": "°C" },
    { "addr": 9, "mnem": "OUT", "name": "Status przekaźników", "access": "R", "kind": "flags",
      "bits": { "0": "EV1", "1": "EV2", "2": "CHILLER", "3": "BOILER" } },
    { "addr": 15, "mnem": "MOT_SET", "name": "Prędkość silnika (set)", "access": "R", "type": "uint16", "scale": 1, "min": 0, "max": 1700 },
    { "addr": 104, "mnem": "STAT", "name": "Flagi statusu", "access": "R", "kind": "flags",
      "bits": { "0": "Mod.Raff", "1": "Mod.Risc", "3": "F.V. H2", "4": "F.V. H4", "6": "B.A.",
                "8": "Antig", "9": "Alrm", "10": "Test", "11": "Stby", "12": "Com err", "13": "H2 asnt", "14": "H4 asnt" } },
    { "addr": 105, "mnem": "ALR_STAT", "name": "Flagi alarmów", "access": "R", "kind": "flags",
      "bits": { "0": "Com", "1": "AIR", "2": "H4", "3": "Acq.Dan H4", "4": "H2", "6": "H4 n.id",
                "7": "Hi Res", "9": "Mot", "10": "SW GRL", "11": "Filter", "12": "2 AIR M5" } },
    { "addr": 200, "mnem": "ADR", "name": "Adres urządzenia", "access": "RW", "type": "uint16", "scale": 1, "min": 1, "max": 255, "default": 1 },
    { "addr": 201, "mnem": "PRG", "name": "Tryb pracy / konfiguracja", "access": "RW", "kind": "flags",
      "bits": { "0-2": { "enum": { "0": "Auto", "1": "Silent", "2": "Night", "3": "Max" } }, "4": "Lock", "7": "Standby" } },
    { "addr": 202, "mnem": "SPL", "name": "Setpoint min", "access": "RW", "type": "uint16", "scale": 0.1, "unit": "°C", "min": 5.0, "max": 35.0, "default": 16.0 },
    { "addr": 203, "mnem": "SPH", "name": "Setpoint max", "access": "RW", "type": "uint16", "scale": 0.1, "unit": "°C", "min": 5.0, "max": 35.0, "default": 28.0 },
    { "addr": 209, "mnem": "E_SAVING", "name": "Offset obecności/stand-by", "access": "RW", "type": "uint16", "scale": 0.1, "unit": "°K", "min": 0, "max": 8.5, "default": 0 },
    { "addr": 210, "mnem": "MVV5", "name": "Min prędkość MIN/Night", "access": "RW", "type": "uint16", "scale": 1, "min": 400, "max": 1500, "default": 400 },
    { "addr": 211, "mnem": "MVV4", "name": "MVV4", "access": "RW", "type": "uint16", "scale": 1, "min": 400, "max": 1500, "default": 550 },
    { "addr": 212, "mnem": "MVV3", "name": "MVV3", "access": "RW", "type": "uint16", "scale": 1, "min": 400, "max": 1500, "default": 680 },
    { "addr": 213, "mnem": "MVV2", "name": "Max w AUTO", "access": "RW", "type": "uint16", "scale": 1, "min": 400, "max": 1500, "default": 1100 },
    { "addr": 214, "mnem": "MVV1", "name": "Max w MAX", "access": "RW", "type": "uint16", "scale": 1, "min": 400, "max": 1500, "default": 1500 },
    { "addr": 215, "mnem": "MVVP1", "name": "MVVP1", "access": "RW", "type": "uint16", "scale": 1, "min": 400, "max": 1700, "default": 1700 },
    { "addr": 218, "mnem": "LLO", "name": "Min woda grzanie", "access": "RW", "type": "uint16", "scale": 0.1, "unit": "°C", "min": 0.0, "max": 100.0, "default": 30.0 },
    { "addr": 219, "mnem": "LHI", "name": "Max woda chłodzenie", "access": "RW", "type": "uint16", "scale": 0.1, "unit": "°C", "min": 0.0, "max": 100.0, "default": 20.0 },
    { "addr": 221, "mnem": "ACL", "name": "Częstotliwość serwisu (h)", "access": "RW", "type": "uint16", "scale": 1, "min": 0, "max": 32000, "default": 0 },
    { "addr": 222, "mnem": "ACL_TIM", "name": "Licznik godzin pracy", "access": "RW", "type": "uint16", "scale": 1, "min": 0, "max": 32000, "default": 0 },
    { "addr": 230, "mnem": "MVVP3", "name": "MVVP3", "access": "RW", "type": "uint16", "scale": 1, "min": 400, "max": 1700, "default": 920 },
    { "addr": 231, "mnem": "SP_ABS", "name": "Setpoint absolutny", "access": "RW", "type": "uint16", "scale": 0.1, "unit": "°C", "min": 5.0, "max": 35.0, "default": 20.0 },
    { "addr": 233, "mnem": "Man", "name": "Sezon auto/ręczny", "access": "RW", "type": "uint16", "scale": 1, "min": 0, "max": 5, "default": 3 },
    { "addr": 234, "mnem": "MVVP2", "name": "MVVP2", "access": "RW", "type": "uint16", "scale": 1, "min": 400, "max": 1500, "default": 1220 },
    { "addr": 242, "mnem": "OS1", "name": "Offset sondy powietrza T1", "access": "RW", "type": "int16", "scale": 0.1, "unit": "°K", "min": -12.0, "max": 12.0, "default": 0 },
    { "addr": 243, "mnem": "OS2", "name": "Offset sondy wody H2", "access": "RW", "type": "int16", "scale": 0.1, "unit": "°K", "min": -12.0, "max": 12.0, "default": 0 },
    { "addr": 244, "mnem": "OS3", "name": "Offset sondy wody H4", "access": "RW", "type": "int16", "scale": 0.1, "unit": "°K", "min": -12.0, "max": 12.0, "default": 0 },
    { "addr": 245, "mnem": "SPL_W", "name": "WEB setpoint min", "access": "RW", "type": "uint16", "scale": 0.1, "unit": "°C", "min": 5.0, "max": 40.0, "default": 20.0 },
    { "addr": 246, "mnem": "SPH_W", "name": "WEB setpoint max", "access": "RW", "type": "uint16", "scale": 0.1, "unit": "°C", "min": 5.0, "max": 40.0, "default": 24.0 },
    { "addr": 247, "mnem": "WEB", "name": "Flagi WEB", "access": "RW", "kind": "flags",
      "bits": { "0": "Led WEB OFF", "1": "Forced off", "2": "Disable rotacji programów", "3": "Disable stby",
                "4": "Inhibit ekstremów", "5": "Restrykcja setpointu", "6": "Disable wszystkich klawiszy",
                "7": "Bypass 1h", "8": "Disable klawisza sezonu" } }
  ]
}
